CHANGES.rst
CONTRIBUTORS.rst
DEVELOP.rst
LICENSE.rst
MANIFEST.in
README.rst
setup.cfg
setup.py
docs/conf.py
docs/index.rst
src/collective/__init__.py
src/collective.collection2xlsx.egg-info/PKG-INFO
src/collective.collection2xlsx.egg-info/SOURCES.txt
src/collective.collection2xlsx.egg-info/dependency_links.txt
src/collective.collection2xlsx.egg-info/entry_points.txt
src/collective.collection2xlsx.egg-info/namespace_packages.txt
src/collective.collection2xlsx.egg-info/not-zip-safe
src/collective.collection2xlsx.egg-info/requires.txt
src/collective.collection2xlsx.egg-info/top_level.txt
src/collective/collection2xlsx/__init__.py
src/collective/collection2xlsx/configure.zcml
src/collective/collection2xlsx/interfaces.py
src/collective/collection2xlsx/permissions.zcml
src/collective/collection2xlsx/setuphandlers.py
src/collective/collection2xlsx/testing.py
src/collective/collection2xlsx/browser/__init__.py
src/collective/collection2xlsx/browser/configure.zcml
src/collective/collection2xlsx/browser/overrides/.gitkeep
src/collective/collection2xlsx/browser/static/.gitkeep
src/collective/collection2xlsx/locales/README.rst
src/collective/collection2xlsx/locales/__init__.py
src/collective/collection2xlsx/locales/collective.collection2xlsx.pot
src/collective/collection2xlsx/locales/update.py
src/collective/collection2xlsx/locales/update.sh
src/collective/collection2xlsx/locales/__pycache__/LC_MESSAGES/collective.collection2xlsx.po
src/collective/collection2xlsx/locales/de/LC_MESSAGES/collective.collection2xlsx.po
src/collective/collection2xlsx/locales/en/LC_MESSAGES/collective.collection2xlsx.po
src/collective/collection2xlsx/profiles/default/actions.xml
src/collective/collection2xlsx/profiles/default/browserlayer.xml
src/collective/collection2xlsx/profiles/default/catalog.xml
src/collective/collection2xlsx/profiles/default/metadata.xml
src/collective/collection2xlsx/profiles/default/rolemap.xml
src/collective/collection2xlsx/profiles/default/registry/main.xml
src/collective/collection2xlsx/profiles/uninstall/browserlayer.xml
src/collective/collection2xlsx/tests/__init__.py
src/collective/collection2xlsx/tests/test_robot.py
src/collective/collection2xlsx/tests/test_setup.py
src/collective/collection2xlsx/tests/test_view_xlsx.py
src/collective/collection2xlsx/tests/robot/test_example.robot
src/collective/collection2xlsx/views/__init__.py
src/collective/collection2xlsx/views/configure.zcml
