Metadata-Version: 2.1
Name: collective.collection2xlsx
Version: 1.0a6
Summary: Excel export for Plone Collections table view.
Home-page: https://github.com/collective/collective.collection2xlsx
Author: Maik Derstappen
Author-email: md@derico.de
License: GPL version 2
Project-URL: PyPI, https://pypi.python.org/pypi/collective.collection2xlsx
Project-URL: Source, https://github.com/collective/collective.collection2xlsx
Project-URL: Tracker, https://github.com/collective/collective.collection2xlsx/issues
Keywords: Python Plone CMS
Platform: UNKNOWN
Classifier: Environment :: Web Environment
Classifier: Framework :: Plone
Classifier: Framework :: Plone :: Addon
Classifier: Framework :: Plone :: 5.2
Classifier: Programming Language :: Python
Classifier: Programming Language :: Python :: 3.7
Classifier: Programming Language :: Python :: 3.8
Classifier: Operating System :: OS Independent
Classifier: License :: OSI Approved :: GNU General Public License v2 (GPLv2)
Requires-Python: >=3.7
Provides-Extra: test
